weightfactors/__init__.py
weightfactors/raking/__init__.py
weightfactors/raking/generalized_raker.py
weightfactors/utils/__init__.py
weightfactors/utils/exceptions.py
weightfactors-0.0.9.dist-info/LICENSE
weightfactors-0.0.9.dist-info/METADATA
weightfactors-0.0.9.dist-info/WHEEL
weightfactors-0.0.9.dist-info/RECORD
