Metadata-Version: 2.1
Name: weightfactors
Version: 0.0.9
Summary: Calculate weight factors for survey data to approximate a representative sample
Author: DemianvG
Author-email: d.vangils@markteffect.nl
Requires-Python: >=3.10,<4.0
Classifier: Programming Language :: Python :: 3
Classifier: Programming Language :: Python :: 3.10
Classifier: Programming Language :: Python :: 3.11
Classifier: Programming Language :: Python :: 3.12
Classifier: Programming Language :: Python :: 3.13
Requires-Dist: numpy (>=2.2.5,<3.0.0)
Requires-Dist: pandas (>=2.2.3,<3.0.0)
